metabase/__init__.py
metabase/metabase.py
metabase-1.4.5.dist-info/LICENSE.md
metabase-1.4.5.dist-info/METADATA
metabase-1.4.5.dist-info/WHEEL
metabase-1.4.5.dist-info/top_level.txt
metabase-1.4.5.dist-info/RECORD
